{
 "Changes": [
  {
   "LogName": "Base Loads",
   "Action": "Load",
   "Priority": "High",
   "Target": "Portraits/{{Lance}}, Characters/{{Lance}}", //Portraits/{{Lance}}, Portraits/{{Lance}}_Spring, Portraits/{{Lance}}_Summer, Portraits/{{Lance}}_Fall, Portraits/{{Lance}}_Winter, Portraits/{{Lance}}_Winter_Outdoor, Portraits/{{Lance}}_Winter_Indoor, Portraits/{{Lance}}_Flower, Portraits/{{Lance}}_Spirit, Portraits/{{Lance}}_Beach, Portraits/{{Lance}}_Wedding, Portraits/{{Lance}}_Xmas, Characters/{{Lance}}, Characters/{{Lance}}_Spring, Characters/{{Lance}}_Summer, Characters/{{Lance}}_Fall, Characters/{{Lance}}_Winter, Characters/{{Lance}}_Winter_Outdoor, Characters/{{Lance}}_Winter_Indoor, Characters/{{Lance}}_Luau, Characters/{{Lance}}_Flower, Characters/{{Lance}}_Spirit, Characters/{{Lance}}_Beach, Characters/{{Lance}}_Xmas
   "FromFile": "assets/{{TargetPathOnly}}/Lance/{{Appearance}}/Lance.png"
  },
  //data/char
  {
   "Action": "EditData",
   "Target": "Data/Characters",
   "Entries": {
    "{{Lance}}": {
     "DisplayName": "{{i18n:Lance}}",
     "BirthSeason": "Spring",
     "BirthDay": 8,
     "HomeRegion": "Town",
     "Language": "Default",
     "Gender": "Undefined",
     "Age": "Adult",
     "Manner": "Polite",
     "SocialAnxiety": "Outgoing",
     "Optimism": "Positive",
     "IsDarkSkinned": true,
     "CanBeRomanced": false, //check events later
     "LoveInterest": null,
     "Calendar": "HiddenUntilMet",
     "SocialTab": "HiddenUntilMet",
     "CanSocialize": true,
     "CanReceiveGifts": true,
     "CanGreetNearbyCharacters": true,
     "CanCommentOnPurchasedShopItems": null,
     "CanVisitIsland": true,
     "IntroductionsQuest": false,
     "ItemDeliveryQuests": null,
     "PerfectionScore": false,
     "EndSlideShow": "TrailingGroup",
     "SpouseAdopts": "PLAYER_HAS_MAIL Current {{ModId}}_Adoption Any",
     "SpouseWantsChildren": "PLAYER_HAS_MAIL Current {{ModId}}_Children Any",
     "SpouseGiftJealousy": false,
     "SpouseGiftJealousyFriendshipChange": -30,
     "SpouseRoom": {
      "MapAsset": "Maps/{{ModId}}_SpouseRoom",
      "MapSourceRect": {
       "X": 0,
       "Y": 0,
       "Width": 6,
       "Height": 9
      }
     },
     "SpousePatio": {
      "MapAsset": "Maps/{{ModId}}_SpousePatio",
      "MapSourceRect": {
       "X": 0,
       "Y": 0,
       "Width": 4,
       "Height": 4
      },
      "SpriteAnimationFrames": [
       [ 0, 0 ]
      ],
      "SpriteAnimationPixelOffset": {
       "X": 0,
       "Y": 0
      }
     },
     "SpouseFloors": [],
     "SpouseWallpapers": [],
     "DumpsterDiveFriendshipEffect": -5,
     "DumpsterDiveEmote": null,
     "FriendsAndFamily": {
     },
     "FlowerDanceCanDance": true,
     "WinterStarGifts": [
      /*
      {
       "Id": "",
       "ItemId": "(O)"
      }
 */
     ],
     "WinterStarParticipant": true,
     "UnlockConditions": "", //{{UnlockConditions}}
     "SpawnIfMissing": true,
     "Home": [ //possibly with marlon and gil/maybe with magnus
      {
       "Id": "{{ModId}}",
       "Condition": "!{{HasMod|contains={{SVETOKEN}}}}",
       "Location": "{{Room}}",
       "Tile": {
        "X": "12",
        "Y": "5"
       },
       "Direction": "2"
      },
      {
       "Id": "{{SVETOKEN}}",
       "Condition": "{{HasMod|contains={{SVETOKEN}}}}",
       "Location": "Custom_Lance_WarpRoom",
       "Tile": {
        "X": 3,
        "Y": 3
       },
       "Direction": "down"
      }
     ],
     "TextureName": "{{Lance}}",
     "Appearance": [],
     "MugShotSourceRect": {},
     "Size": {
      "X": 16,
      "Y": 32
     },
     "Breather": true,
     "BreathChestRect": null,
     "BreathChestPosition": null,
     "Shadow": null,
     "EmoteOffset": {
      "X": 0,
      "Y": 0
     },
     "ShakePortraits": [ 15 ],
     "KissSpriteIndex": 28,
     "KissSpriteFacingRight": true,
     "HiddenProfileEmoteSound": "newRecipe",
     "HiddenProfileEmoteDuration": 4000,
     "HiddenProfileEmoteStartFrame": 32,
     "HiddenProfileEmoteFrameCount": 2,
     "HiddenProfileEmoteFrameDuration": 200.0,
     "FormerCharacterNames": [],
     "CustomFields": {
     }
    }
   }
  },
  {
   "Action": "EditData",
   "Target": "Data/NPCGiftTastes",
   "Entries": {
    "{{Lance}}": "{{i18n:Gifts.Loved}}/218 BasiliskPaw IceRod MagicQuiver 907 896 {{SVEToken}}_Golden_Goose_Egg {{SVEToken}}_Prismatic_Pop {{SVEToken}}_Pineapple_Custard_Crepe {{SVEToken}}_Void_Shard {{SVEToken}}_Torpedo_Trout {{SVEToken}}_Swirl_Stone {{SVEToken}}_Ornate_Treasure_Chest {{SVEToken}}_Monster_Mushroom {{SVEToken}}_Green_Mushroom {{SVEToken}}_Gemfish {{SVEToken}}_Daggerfish {{SVEToken}}_Aged_Blue_Moon_Wine/{{i18n:Gifts.Liked}}/257 {{SVEToken}}_Chocolate_Truffle_Bar {{SVEToken}}_Gold_Carrot 281 422 886 905 74 797 261 688 689 690 446 96 97 98 99 121 122 158 159 161 160 162 163 166 305 306 704 909 857 {{SVEToken}}_Void_Soul {{SVEToken}}_Void_Salmon_Sushi {{SVEToken}}_Void_Root {{SVEToken}}_Void_Pebble {{SVEToken}}_Void_Delight {{SVEToken}}_Undeadfish {{SVEToken}}_Smelly_Rafflesia {{SVEToken}}_Slime_Berry {{SVEToken}}_Shiny_Lunaloo {{SVEToken}}_Salal_Berry {{SVEToken}}_Rusty_Blade {{SVEToken}}_Razor_Trout {{SVEToken}}_Radioactive_Bass {{SVEToken}}_Puppyfish {{SVEToken}}_Mushroom_Berry_Rice {{SVEToken}}_Monster_Fruit {{SVEToken}}_Meteor_Carp {{SVEToken}}_Lunaloo {{SVEToken}}_Lightning_Elixir {{SVEToken}}_Kittyfish {{SVEToken}}_King_Salmon {{SVEToken}}_Hero_Elixir {{SVEToken}}_Haste_Elixir {{SVEToken}}_Gravity_Elixir {{SVEToken}}_Goldenfish {{SVEToken}}_Golden_Ocean_Flower {{SVEToken}}_Butterfish {{SVEToken}}_Bonefish {{SVEToken}}_Bearberrys {{SVEToken}}_Barbarian_Elixir {{SVEToken}}_Armor_Elixir {{SVEToken}}_Aegis_Elixir/{{i18n:Gifts.Disliked}}/-80 -74 338 80 82/{{i18n:Gifts.Hated}}/-81 330 283 206 211 216 233 234 245 220 221 222 223 224 279 612 611 608 604/{{i18n:Gifts.Neutral}}/-4 -28 286 287 288 829 396 393 397 392 394 {{SVEToken}}_Stamina_Capsule {{SVEToken}}_Sports_Drink {{SVEToken}}_Baby_Lunaloo 404 {{SVEToken}}_Mushroom_Colony 420/"
   }
  },
  {
   "LogName": "NPC animationDescriptions edit",
   "Action": "EditData",
   "Target": "Data/animationDescriptions",
   "Entries": {
    "{{Lance}}_stand": "0/0/0",
    "{{Lowercase:{{Lance}}_sleep}}": "16/16/16",
    "{{Lance}}_Sword": "17/17 17 17 17 17 17 18 18 18 18 18 18 18 18 17 17 17 17 17 17 18 18 18 18 18 18 17 17 17 17 17 18 18 18/18",
    "{{Lance}}_NoddingKneel": "21/21 21 21 22 22 22 21 21 21 23 23 23 21 21 21 22 22 22 21 21 21 23 23 23 21 21 21/21",
    "{{Lance}}_NoddingStand": "41/41 41 41 42 42 42 41 41 41 43 43 43 41 41 41 42 42 42 41 41 41 43 43 43 41 41 41/41",
    "{{Lance}}_LeftWag": "12/12 12 12 31 31 31 12 12 12 31 31 31 12 12 12 31 31 31 12 12 12 31 31 31 12 12 12/12"
   }
  },
  {
   "Action": "EditData",
   "Target": "Data/NPCGiftTastes",
   "When": {
    "Relationship:{{Lance}}": "Married"
   },
   "TextOperations": [
    {
     "Operation": "Append",
     "Target": [ "Fields", "{{Lance}}", "1" ],
     "Value": "{{ModId}}_Khanjar {{ModId}}_Book {{ModId}}_camping {{ModId}}_mishaps {{ModId}}_Rope {{ModId}}_shenanigans {{ModId}}_Razor 96 97 98 99 103 104 107 109 114 121 122 124 125 16 18 20 22 24 78 88 90 92 174 176 178 180 182 184 186 188 190 182 218 245 246 247 248 250 251 252 254 256 257 258 259 260 262 264 266 268 270 271 272 274 276 278 280 281 282 283 284 290 296 300 303 304 305 306 307 308 334 335 336 337 338 340 342 346 348 350 368 369 370 371 372 373 376 396 397 398 399 400 402 404 406 408 410 412 414 416 417 423 Aviroen.Mycology_TomYueaPhai {{SVEToken}}_Void_Soul {{SVEToken}}_Swirl_Stone {{SVEToken}}_Dewdrop_Berry {{SVEToken}}_Frog {{SVEToken}}_Kittyfish {{SVEToken}}_Blue_Moon_Wine {{SVEToken}}_Age_Blue_Moon_Wine {{SVEToken}}_Void_Shard {{SVEToken}}_Baby_Lunaloo {{SVEToken}}_Undeadfish {{SVEToken}}_Gemfish {{SVEToken}}_Goldenfish {{SVEToken}}_Monster_Fruit {{SVEToken}}_Void_Eel {{SVEToken}}_Torpedo_Trout {{SVEToken}}_Lunaloo {{SVEToken}}_Shiny_Lunaloo {{SVEToken}}_Radioactive_Bass {{SVEToken}}_Slime_Berry {{SVEToken}}_Void_Root {{SVEToken}}_Monster_Mushroom {{SVEToken}}_Frog_Legs {{SVEToken}}_Void_Delight {{SVEToken}}_Void_Salmon_Sushi {{SVEToken}}_Grampleton_Orange_Chicken {{SVEToken}}_Baked_Berry_Oatmeal {{SVEToken}}_Big_Bark_Burger {{SVEToken}}_Flower_Cookie {{SVEToken}}_Glazed_Butterfish {{SVEToken}}_Mixed_Berry_Pie {{SVEToken}}_Mushroom_Berry_Rice {{SVEToken}}_Seaweed_Salad",
     "Delimiter": " "
    }
   ]
  },
  {
   "Action": "EditData",
   "Target": "Characters/Schedules/{{Lance}}",
   "When": {
    "HasMod |contains={{SVEToken}}": false
   },
   "Entries": {
    "spring": "610 {{Room}} 10 10 0",
    "{{Lance}}_Mon": "610 {{Room}} 10 10 0/1200 WizardHouse 5 14 2 {{Lance}}_NoddingStand/1900 {{Room}} 6 15 3 {{Lance}}_Special1/2600 {{Room}} 14 4 1 {{Lance}}_sleep",
    "{{Lance}}_Tue": "610 {{Room}} 10 10 0/1200 Forest 88 50 1/2600 {{Room}} 14 4 1 {{Lance}}_sleep",
    "{{Lance}}_Wed": "610 {{Room}} 10 10 0/1200 Forest 100 73 1/2600 {{Room}} 14 4 1 {{Lance}}_sleep",
    "{{Lance}}_Thu": "610 {{Room}} 10 10 0/1200 Forest 48 99 2 {{Lance}}_NoddingStand/2600 {{Room}} 14 4 1 {{Lance}}_sleep",
    "{{Lance}}_Fri": "610 {{Room}} 10 10 0/1200 WizardHouse 5 14 2 {{Lance}}_NoddingKneel/1900 {{Room}} 6 15 3 {{Lance}}_Special1/2600 {{Room}} 14 4 1 {{Lance}}_sleep",
    "{{Lance}}_Sat": "610 {{Room}} 10 10 0/1200 WizardHouse 5 14 2 {{Lance}}_NoddingStand/1900 {{Room}} 6 15 3 {{Lance}}_Special1/2600 {{Room}} 14 4 1 {{Lance}}_sleep",
    "{{Lance}}_Sun": "610 {{Room}} 10 10 0/1200 WizardHouse 5 14 2 {{Lance}}_NoddingStand/1900 {{Room}} 6 15 3 {{Lance}}_Special1/2600 {{Room}} 14 4 1 {{Lance}}_sleep"
   }
  },
  {
   "LogName": "Lance's Room Data/Location",
   "Action": "EditData",
   "Target": "Data/Locations",
   "Entries": {
    "{{Room}}": {
     "DisplayName": "{{i18n:Room}}",
     "DefaultArrivalTile": {
      "X": 9,
      "Y": 14
     },
     "CreateOnLoad": {
      "MapPath": "Maps\\{{Room}}",
      "AlwaysActive": false
     },
     "MusicDefault": "Plums"
    }
   }
  },
  {
   "LogName": "{{Room}} EditMap",
   "Action": "EditMap",
   "Target": "Maps/{{Room}}",
   "AddWarps": [
    "9 19 Forest 10 35"
   ]
  }
 ]
}
